HarmonyMIDIToken/__init__.py
HarmonyMIDIToken/tokenizer.py
harmony_midi_token-1.1.0.dist-info/licenses/LICENSE
harmony_midi_token-1.1.0.dist-info/METADATA
harmony_midi_token-1.1.0.dist-info/WHEEL
harmony_midi_token-1.1.0.dist-info/top_level.txt
harmony_midi_token-1.1.0.dist-info/RECORD
