Metadata-Version: 2.4
Name: harmony-midi-token
Version: 1.1.0
Summary: The Brand New Midi Tokenizer based on Music21
Author-email: rrayy <taejunham1@gmail.com>
License: MIT
Requires-Python: >=3.11
License-File: LICENSE
Requires-Dist: music21>=8.3.0
Requires-Dist: pychord>=1.2.2
Dynamic: license-file
